{
  "collection": "memberships_shifts_skills",
  "field": "memberships_id",
  "related_collection": "memberships",
  "meta": {
    "junction_field": "shifts_skills_id",
    "many_collection": "memberships_shifts_skills",
    "many_field": "memberships_id",
    "one_allowed_collections": null,
    "one_collection": "memberships",
    "one_collection_field": null,
    "one_deselect_action": "nullify",
    "one_field": "shifts_skills",
    "sort_field": null
  },
  "schema": {
    "table": "memberships_shifts_skills",
    "column": "memberships_id",
    "foreign_key_table": "memberships",
    "foreign_key_column": "id",
    "constraint_name": "memberships_shifts_skills_memberships_id_foreign",
    "on_update": "NO ACTION",
    "on_delete": "SET NULL"
  }
}
